{
  "$schema": "https://developer.microsoft.com/json-schemas/fabric/item/report/definition/visualContainer/2.6.0/schema.json",
  "name": "2a2c212d6818130ed54c",
  "position": {
    "x": 649.44966442953023,
    "y": 274.04026845637583,
    "z": 1004,
    "height": 300.67114093959731,
    "width": 298.95302013422821,
    "tabOrder": 1004
  },
  "visual": {
    "visualType": "clusteredColumnChart",
    "query": {
      "queryState": {
        "Category": {
          "projections": [
            {
              "field": {
                "Column": {
                  "Expression": {
                    "SourceRef": {
                      "Entity": "Encuesta"
                    }
                  },
                  "Property": "tipo suscripcion"
                }
              },
              "queryRef": "Encuesta.tipo suscripcion",
              "nativeQueryRef": "Tipo de suscripción",
              "active": true,
              "displayName": "Tipo de suscripción"
            }
          ]
        },
        "Y": {
          "projections": [
            {
              "field": {
                "Measure": {
                  "Expression": {
                    "SourceRef": {
                      "Entity": "Encuesta"
                    }
                  },
                  "Property": "Media_tasa_completitud_porcentaje"
                }
              },
              "queryRef": "Encuesta.Media_tasa_completitud_porcentaje",
              "nativeQueryRef": "Media_tasa_completitud_porcentaje"
            }
          ]
        }
      },
      "sortDefinition": {
        "sort": [
          {
            "field": {
              "Measure": {
                "Expression": {
                  "SourceRef": {
                    "Entity": "Encuesta"
                  }
                },
                "Property": "Media_tasa_completitud_porcentaje"
              }
            },
            "direction": "Descending"
          }
        ],
        "isDefaultSort": true
      }
    },
    "visualContainerObjects": {
      "title": [
        {
          "properties": {
            "text": {
              "expr": {
                "Literal": {
                  "Value": "'Tasa promedio de completitud según tipo de suscripción'"
                }
              }
            },
            "fontFamily": {
              "expr": {
                "Literal": {
                  "Value": "'''Segoe UI'', wf_segoe-ui_normal, helvetica, arial, sans-serif'"
                }
              }
            },
            "alignment": {
              "expr": {
                "Literal": {
                  "Value": "'center'"
                }
              }
            }
          }
        }
      ],
      "divider": [
        {
          "properties": {
            "show": {
              "expr": {
                "Literal": {
                  "Value": "true"
                }
              }
            },
            "color": {
              "solid": {
                "color": {
                  "expr": {
                    "ThemeDataColor": {
                      "ColorId": 2,
                      "Percent": 0
                    }
                  }
                }
              }
            }
          }
        }
      ]
    },
    "drillFilterOtherVisuals": true
  }
}